{
  "template": {
    "_links": {
      "self": {
        "href": "https://api.pingone.com/v1/environments/0ce2b42c-7022-46a8-923a-c04cf0d91a25/templates/strong_authentication"
      },
      "environment": {
        "href": "https://api.pingone.com/v1/environments/0ce2b42c-7022-46a8-923a-c04cf0d91a25"
      }
    },
    "id": "strong_authentication",
    "environment": {
      "id": "0ce2b42c-7022-46a8-923a-c04cf0d91a25"
    },
    "description": "Users will receive this message for strong authentication.",
    "deliveryMethods": [
      "SMS",
      "Email",
      "Push",
      "Voice",
      "WhatsApp"
    ],
    "displayName": "Strong Authentication",
    "createdAt": "2018-12-10T10:45:05.000Z",
    "updatedAt": "2018-12-10T10:45:05.000Z",
    "variables": {
      "user.username": {
        "required": false
      },
      "user.name.given": {
        "required": false
      },
      "user.name.family": {
        "required": false
      },
      "current-year": {
        "required": false
      },
      "otp": {
        "required": true,
        "requiredForDeliveryMethods": [
          "SMS",
          "Email",
          "Voice"
        ]
      }
    },
    "allowDynamicVariables": true
  },
  "contents": [
    {
      "_links": {
        "template": {
          "href": "https://api.pingone.com/v1/environments/0ce2b42c-7022-46a8-923a-c04cf0d91a25/templates/strong_authentication"
        },
        "environment": {
          "href": "https://api.pingone.com/v1/environments/0ce2b42c-7022-46a8-923a-c04cf0d91a25"
        },
        "self": {
          "href": "https://api.pingone.com/v1/environments/0ce2b42c-7022-46a8-923a-c04cf0d91a25/templates/strong_authentication/contents/2545f629-c4c0-428b-8974-c8f4bf453ce3"
        }
      },
      "id": "2545f629-c4c0-428b-8974-c8f4bf453ce3",
      "environment": {
        "id": "0ce2b42c-7022-46a8-923a-c04cf0d91a25"
      },
      "createdAt": "2026-01-13T01:16:52.961Z",
      "updatedAt": "2026-01-13T01:16:52.961Z",
      "locale": "en",
      "template": {
        "id": "strong_authentication"
      },
      "content": "<repeatMessage val=2>Hello <pause1sec> this is The Marriott Vacation Clubs <pause1sec> your multi-factor authentication code is <sayCharValue>${otp}</sayCharValue><pause1sec> Do not share this code with anyone. <pause1sec> Thank you for helping us keep your account secure. </repeatMessage>",
      "deliveryMethod": "Voice",
      "default": false
    },
    {
      "_links": {
        "template": {
          "href": "https://api.pingone.com/v1/environments/0ce2b42c-7022-46a8-923a-c04cf0d91a25/templates/strong_authentication"
        },
        "environment": {
          "href": "https://api.pingone.com/v1/environments/0ce2b42c-7022-46a8-923a-c04cf0d91a25"
        },
        "self": {
          "href": "https://api.pingone.com/v1/environments/0ce2b42c-7022-46a8-923a-c04cf0d91a25/templates/strong_authentication/contents/7cfe82ac-f66c-4342-ab0a-6320499b2e14"
        }
      },
      "id": "7cfe82ac-f66c-4342-ab0a-6320499b2e14",
      "environment": {
        "id": "0ce2b42c-7022-46a8-923a-c04cf0d91a25"
      },
      "createdAt": "2026-01-13T01:16:51.101Z",
      "updatedAt": "2026-01-13T01:16:51.101Z",
      "locale": "en",
      "template": {
        "id": "strong_authentication"
      },
      "subject": "Your Secure Sign-in Verification Code",
      "body": "<!DOCTYPE HTML PUBLIC \"-//W3C//DTD HTML 4.01 Transitional//EN\" \"http://www.w3.org/TR/html4/loose.dtd\">\n<html lang=\"en\" dir=\"ltr\" xmlns:o=\"urn:schemas-microsoft-com:office:office\">\n<head>\n<meta content=\"text/html; charset=utf-8\" http-equiv=\"Content-Type\">\n<meta content=\"width=device-width, initial-scale=1, maximum-scale=1\" name=\"viewport\">\n<meta content=\"IE=edge\" http-equiv=\"X-UA-Compatible\">\n<meta name=\"color-scheme\" content=\"light dark\">\n<meta name=\"supported-color-schemes\" content=\"light dark\">\n<title>Your Exclusive Offer</title>\n<!--[if mso]>\n<style type=\"text/css\" media=\"all\">\ntable, tr, td {font-size:0px; line-height:0px; border-collapse:collapse; mso-hyphenate:none;}\na {text-decoration:none;}\n</style>\n<xml>\n<o:OfficeDocumentSettings>\n<o:AllowPNG/>\n<o:PixelsPerInch>96</o:PixelsPerInch>\n</o:OfficeDocumentSettings>\n</xml>\n<![endif]-->\n<style type=\"text/css\">\n*{-webkit-text-size-adjust:100%;}\n*{-webkit-font-smoothing:antialiased;}\n*{-ms-text-size-adjust:100%;}\n*{-moz-osx-font-smoothing:grayscale;}\n*{-ms-font-smoothing:antialiased;}\ntable td {border-collapse:collapse; mso-table-lspace:0pt; mso-table-rspace:0pt;}\ntable {border-collapse:collapse; mso-table-lspace:0pt; mso-table-rspace:0pt; margin:0 auto !important;}\nbody {margin:0px auto;}\n.ExternalClass {width:100%;}\n.ExternalClass, .ExternalClass p, .ExternalClass span, .ExternalClass font, .ExternalClass td, .ExternalClass div {line-height:100%;}\n.nowrap {white-space:nowrap;}\n@media (prefers-color-scheme:light) {\n.appleLinksIndigo a {color:#082940 !important; text-decoration:none !important;}\n.appleLinksGray a {color:#666666 !important;}\n.appleLinksGrayNoUnderline a {color:#666666 !important; text-decoration:none !important;}\n.appleLinksWhite a, .appleLinksWhite {color:#ffffff !important; text-decoration:none !important;}\n.appleLinksCopper a {color:#a45d23 !important; text-decoration:none !important;}\n.appleLinksLightCopper a {color:#c79f79 !important; text-decoration:none !important;}\n}\n@media (prefers-color-scheme:dark) {\n.appleLinksDarkModeWhite a, .appleLinksDarkModeWhite {color:#ffffff !important; text-decoration:none !important;}\n.appleLinksDarkModeCopper a, .appleLinksDarkModeCopper {color:#d69b69 !important; text-decoration:none !important;}\n.appleLinksDarkModeLightCopper a, .appleLinksDarkModeLightCopper {color:#c79f79 !important; text-decoration:none !important;}\n.appleLinksDarkModeGray a, .appleLinksDarkModeGray {color:#eeeeee !important;}\n.appleLinksDarkModeGrayNoUnderline a, .appleLinksDarkModeGrayNoUnderline {color:#eeeeee !important; text-decoration:none !important;}\n.appleLinksDarkModeDarkGray a, .appleLinksDarkModeDarkGray {color:#cccccc !important;}\n.appleLinksDarkModeDarkGrayNoUnderline a, .appleLinksDarkModeDarkGrayNoUnderline {color:#cccccc !important; text-decoration:none !important;}\t\n.darkHide {display:none !important; visibility:hidden !important;}\n.darkShow {display:inline-block !important; visibility:visible !important;}\n.backgroundPitch {background-color:#000000 !important;}\n.backgroundBlack {background-color:#252525 !important;}\n.backgroundLightBlack {background-color:#333333 !important;}\n.backgroundCharcoal {background-color:#3c3c3c !important;}\n.backgroundSmoke {background-color:#4c4c4c !important;}\n.backgroundIndigo {background-color:#082940 !important;}\n.backgroundLightIndigo {background-color:#2D495D !important;}\n.colorDarkGray {color:#cccccc !important;}\n.buttonGray {border:1px solid #eeeeee !important;}\n.buttonSmallShow {width:129px !important; height:29px !important; max-height:29px !important;}\n.buttonLargeShow {width:241px !important; height:49px !important; max-height:49px !important;}\n.copperRule {filter:saturate(60%)brightness(160%)}   \n.colorGray {color:#eeeeee !important;}    \n}\n@media handheld, only screen and (max-width:480px) {\n.wrapper {width:100% !important; max-width:100% !important;}\n.wrapper98 {width:98% !important; max-width:100% !important;}\n.wrapper-50 {width:calc(100% - 50px) !important; max-width:90% !important;}\n.fullWidth {display:flex !important; width:auto !important;}\nimg.fullWidth {width:100% !important; margin:0 auto !important; height:auto !important;}\n.width70 {width:70px !important; max-width:70px !important;}\n.logoSmall {width:75% !important; max-width:75% !important;}\n.promoSmall {width:70% !important; max-width:70% !important;}\n.button {width:210px !important; height:42px !important; font-size:17px !important; line-height:42px !important;}\n.buttonPhone {width:220px !important; height:42px !important; font-size:20px !important; line-height:42px !important;}.hide {display:none !important; visibility:hidden !important;}\n.show {display:block !important; visibility:visible !important;}\n.showInline {display:inline-block !important; visibility:visible !important;}\n.autoHeight {height:auto !important;}\n.alignLeft{float:left !important; text-align:left !important;}\n.alignCenter {text-align:center !important; align:center !important; margin:0 auto !important;}\n.backgroundWhite {background-color:#ffffff !important;}\n.backgroundLinen {background-color:#F2F2F2 !important;}\n.perStay {font-size:20px !important; line-height:50px !important; color:#7BECD5 !important;}\n.padtop0 {padding-top:0px !important;}\n.padtop5 {padding-top:5px !important;}\n.padtop10 {padding-top:10px !important;}\n.padtop15 {padding-top:15px !important;}\n.padtop25 {padding-top:25px !important;}\n.padtop30 {padding-top:30px !important;}\n.padtop35 {padding-top:35px !important;}\n.padtop40 {padding-top:40px !important;}\n.padtop50 {padding-top:50px !important;}\n.padbottom0 {padding-bottom:0px !important;}\n.padbottom5 {padding-bottom:5px !important;}\n.padbottom10 {padding-bottom:10px !important;}\n.padbottom15 {padding-bottom:15px !important;}\n.padbottom20 {padding-bottom:20px !important;}\n.padbottom25 {padding-bottom:25px !important;}\n.padbottom30 {padding-bottom:30px !important;}\n.padbottom40 {padding-bottom:40px !important;}\n.padbottom50 {padding-bottom:50px !important;}\n.padleftright2 {padding-left:2px !important; padding-right:2px !important;}\n.padleftright20 {padding-left:20px !important; padding-right:20px !important;}\n.padleftright9P {padding-left:9% !important; padding-right:9% !important;}\n.font9 {font-size:9px !important; line-height:15px !important;}\n.font12 {font-size:12px !important; line-height:16px !important;}\n.font12plus {font-size:12px !important; line-height:18px !important;}\n.font14 {font-size:14px !important; line-height:22px !important;}\n.font15 {font-size:15px !important; line-height:23px !important;}\n.font16 {font-size:16px !important; line-height:25px !important;}\n.font17 {font-size:17px !important; line-height:25px !important;}\n.font18 {font-size:18px !important; line-height:28px !important;}\n.font19 {font-size:19px !important; line-height:24px !important;}\n.font22 {font-size:22px !important; line-height:34px !important;}\n.font28 {font-size:28px !important; line-height:34px !important;}\n.font30 {font-size:30px !important; line-height:36px !important;}\n.font60 {font-size:60px !important; line-height:60px !important;}\n.fontBonus {font-size:14px !important; line-height:45px !important; vertical-align:1em !important;}\n}\n@media handheld, only screen and (max-width:380px) {\n.promoSmall {width:calc(100% - 50px) !important; max-width:90% !important;}\n}\n/* // FOOTER STYLES // OPEN */\t\n.footerNoWrap {white-space:nowrap;}\n@media (prefers-color-scheme:light) {\n.footerAppleLinks a, .footerAppleLinks {color:#666666 !important;}\n.footerAppleLinksNoUnderline a, .footerAppleLinksNoUnderline {color:#666666 !important; text-decoration:none !important;}\n.footerLinks a, .footerLinks {color:#666666 !important;}\n.footerLinksNoUnderline a, .footerLinksNoUnderline {color:#666666 !important; text-decoration:none !important;}\n}\n@media (prefers-color-scheme:dark) {\n.footerDarkAppleLinks a, .footerDarkAppleLinks {color:#cccccc !important;}\n.footerDarkAppleLinksNoUnderline a, .footerDarkAppleLinksNoUnderline {color:#cccccc !important; text-decoration:none !important;}\n.footerDarkLinks a, .footerDarkLinks {color:#cccccc !important;}\n.footerDarkLinksNoUnderline a, .footerDarkLinksNoUnderline {color:#cccccc !important; text-decoration:none !important;}\n.footerDarkColor {color:#cccccc !important;}\n.footerDarkDesktopShow {display:inline-block !important; visibility:visible !important;}\n.footerLightDesktopHide {display:none !important; visibility:hidden !important;}\t\n.footerDarkEho {filter:saturate(0%)brightness(150%)}\n}\n@media handheld, only screen and (max-width:480px) {\n.footerWrapper {width:100% !important; max-width:100% !important;}\n.footerwrapper98 {width:98% !important; max-width:100% !important;}\n.footerHide {display:none !important; visibility:hidden !important;}\n.footerShow {display:block !important; visibility:visible !important;}\n.footerEhoShow {display:block !important; visibility:visible !important; line-height:.5em !important;}\n.footerAutoHeight {height:auto !important;}\n.footerLeft {float:left !important; text-align:left !important;}\n.footerCenter {text-align:center !important; align:center !important; margin:0 auto !important;}\n.footerPad2 {padding-left:2px !important; padding-right:2px !important;}\n}\n@media handheld, only screen and (max-width:480px) and (prefers-color-scheme:light){\n.footerLightMobileShow {display:inline-block !important; visibility:visible !important;}\n.footerLightDesktopHide {display:none !important; visibility:hidden !important;}\t\n.footerDarkMobileHide {display:none !important; visibility:hidden !important;}\n}\n@media handheld, only screen and (max-width:480px) and (prefers-color-scheme:dark){\n.footerLightDesktopHide {display:none !important; visibility:hidden !important;}\t\n.footerDarkDesktopHide {display:none !important; visibility:hidden !important;}\n.footerDarkMobileShow {display:inline-block !important; visibility:visible !important;}\n}\n/* // FOOTER STYLES // CLOSE */\t\n</style>\n</head>\n<body class=\"backgroundPitch\" style=\"background-color:#F2F2F2;\">\n\n\t\n<!--------------------------------------------------------\n\tSUBJECT LINE FOR INITIAL & ITD: %%first_name%%, your exclusive savings event is here\n\t\n\tSUBJECT LINE FOR CHASE & CTD: %%first_name%%, your exclusive vacation offer ends soon\n\n\tHIDDEN PREVIEW TEXT: Choose your destination from $199 + Bonus Gift.\n---------------------------------------------------------> \n\t\n\t\n<!-- BACKGROUND COLOR FIXES // OPEN // -->\n<div class=\"backgroundPitch\" style=\"background-color:#F2F2F2;\">\n<table role=\"presentation\" class=\"backgroundPitch\" style=\"background-color:#F2F2F2;\" width=\"100%\"><tr><td class=\"backgroundPitch\" style=\"background-color:#F2F2F2;\">\n\t       <!-- Envelope for presentation | BEGIN -->\n <!-- Envelope for presentation | END -->\n<!-- CONTENT // OPEN // -->\n<!-- PADDING // OPEN // -->\n<table role=\"presentation\" align=\"center\" border=\"0\" cellpadding=\"0\" cellspacing=\"0\" class=\"wrapper\" style=\"border:none; border-collapse:collapse; mso-table-lspace:0pt; mso-table-rspace:0pt; width:640px;\" width=\"640\">\n\t<tr>\n\t\t<td class=\"padtop10\" style=\"padding-top:30px;\" align=\"center\"></td>\n\t</tr>\n</table>\n<!-- PADDING // CLOSE // -->\n<!-- LOGO // OPEN // -->\n<table role=\"presentation\" align=\"center\" border=\"0\" cellpadding=\"0\" cellspacing=\"0\" class=\"wrapper98 backgroundPitch\" style=\"background-color:#F2F2F2; border:none; border-collapse:collapse; mso-table-lspace:0pt; mso-table-rspace:0pt; text-align:center; width:640px;\" width=\"640\">\n\t<!-- LIGHT MODE LOGO // OPEN // -->\n\t<tr class=\"darkHide\">\n\t\t<td class=\"padleftright20 padbottom30\" style=\"padding-top:15px; padding-right:0px; padding-bottom:40px; padding-left:0px;\" align=\"center\">\n\t\t\t<img class=\"logoSmall autoHeight\" border=\"0\" alt=\"The Marriott Vacation Clubs: Marriott Vacation Club, Sheraton Vacation Club, and Westin Vacation Club\" src=\"https://s3.amazonaws.com/tmvc-email-static/email-footers/TMVC_LOGO_1LINE_K.png\" style=\"display:inline-block;\" width=\"360\" height=\"14\">\n\t\t</td>\n\t</tr>\n\t<!-- LIGHT MODE LOGO // CLOSE // -->\n\t<!-- DARK MODE LOGO // OPEN // -->\n\t<tr class=\"darkShow\" style=\"display:none; visibility:hidden; text-align:center;\" align=\"center\">\n\t\t<td class=\"padleftright20 padbottom30\" style=\"padding-top:15px; padding-right:0px; padding-bottom:40px; padding-left:0px; text-align:center;\" align=\"center\">\n\t\t\t<img class=\"logoSmall autoHeight\" border=\"0\" alt=\"The Marriott Vacation Clubs: Marriott Vacation Club, Sheraton Vacation Club, and Westin Vacation Club\" src=\"https://s3.amazonaws.com/tmvc-email-static/email-footers/TMVC_LOGO_1LINE_W.png\" style=\"display:inline-block;\" width=\"360\" height=\"14\">\n\t\t</td>\n\t</tr>\n\t<!-- DARK MODE LOGO // CLOSE // -->\n</table>\n<!-- LOGO // CLOSE // -->\n\n   \n\n<table bgcolor=\"#FFFFFF\" role=\"presentation\" align=\"center\" border=\"0\" cellpadding=\"0\" cellspacing=\"0\" class=\"wrapper98\" style=\"background-color:#FFFFFF; border:none; border-collapse:collapse; mso-table-lspace:0pt; mso-table-rspace:0pt; width:640px;\" width=\"640\">\n\t\n    \n                     <tr>\n                        \n                        <td class=\"padtop40 padbottom5 padleftright25 font28\" style=\"padding-top:50px; padding-right:40px; padding-bottom:8px; padding-left:40px; color:#082940; font-size:46px; line-height:52px; mso-line-height-rule:exactly; font-family:'Lucida Grande', Lucida Sans Unicode, Lucida Sans, sans-serif; text-align:left; text-transform: uppercase;\">Your Secure Sign&#8209;in Verification Code</td>\n                     </tr>\n               \n                     <tr>\n                        <td class=\"padleftright25 padtop10\" style=\"padding-top:15px; padding-right:40px; padding-bottom:20px; padding-left:40px;\"><img alt=\"\" border=\"0\" class=\"autoHeight copperRule width70\" src=\"https://mvc-email-static.s3.amazonaws.com/2022/22-02-1899950/rule.jpg\" style=\"display:block;\" width=\"96\" height=\"2\"></td>\n                     </tr>\n          \n                  <!-- HEADLINE // CLOSE // -->\n                  <!-- MAIN CONTENT // OPEN // -->\n                     <tr>\n                        <td class=\"padleftright25  padbottom40 font18\" style=\"padding-top:0px; padding-right:40px; padding-bottom:50px; padding-left:40px; color:#082940; font-size:18px; line-height:29px; font-family:Arial, sans-serif; text-align:left;\">\n                   \nHello  <span style=\"color:magenta\">${user.name.given}</span>,\n\t\t\t\t\t\t\t<br>\n<br>\nTo complete your authentication, please use the verification code below:<br><br>\n\t\t\t\t\t\t\t<span style=\"color:magenta; font-size:26px\">${otp}</span><br><br>\n\t\t\t\t\t\t  Do not share this code with anyone. This code will expire in <br class=\"hide\">10 minutes. \n<br><br>\nIf you did not request this code, you can safely ignore this message. For assistance, please <a href=\"https://www.marriottvacationclubs.com/s/contact-us\" target=\"_blank\" style=\"color:#082940; text-decoration:underline;\" title=\"#\">contact us</a>. \t\t\n<br><br>\nThank you for helping us keep your account secure. \n\n\n\n                        </td>\n                     </tr>\n\n\t\t\t\t\t  \t\t\n\n    \n\n<!-- MAIN CONTENT // CLOSE // -->\n        </table>\n<!-- CTA // CLOSE // -->\n<!-- CONTENT // CLOSE // -->\n<!-- FOOTER // OPEN // -->\n<table role=\"presentation\" class=\"footerwrapper98\" border=\"0\" cellspacing=\"0\" cellpadding=\"0\" align=\"center\" style=\"border:none; border-collapse:collapse; mso-table-lspace:0pt; mso-table-rspace:0pt; width:640px;\" width=\"640\">\n\t<!-- BRANDBAR DESKTOP // OPEN // -->\n\t<tr class=\"footerLightDesktopHide\">\n\t\t<td align=\"center\" style=\"padding-top:46px;padding-bottom:10px;\">\n\t\t\t<a href=\"https://www.marriottvacationclubs.com\" target=\"_blank\">\n\t\t\t\t<img src=\"https://s3.amazonaws.com/tmvc-email-static/email-footers/5_brandbar-desktop.png\" alt=\"The Marriott Vacation Clubs: Marriott Vacation Club, Sheraton Vacation Club, Westin Vacation Club\" style=\"display:inline-block; width:638px; height:95px;\" width=\"638\" height=\"95\">\n\t\t\t</a>\n\t\t</td>\n\t</tr>\n\t<!-- BRANDBAR DESKTOP // CLOSE // -->\n\t<!-- BRANDBAR MOBILE // OPEN // -->\n\t<tr class=\"footerLightMobileShow\" style=\"display:none;\">\n\t\t<td align=\"center\" style=\"padding-top:36px; padding-bottom:10px; text-align:center;\">\n\t\t\t<a href=\"https://www.marriottvacationclubs.com\" target=\"_blank\">\n\t\t\t\t<img class=\"footerWrapper footerAutoHeight\" src=\"https://s3.amazonaws.com/tmvc-email-static/email-footers/5_brandbar-mobile.png\" alt=\"The Marriott Vacation Clubs: Marriott Vacation Club, Sheraton Vacation Club, Westin Vacation Club\" style=\"display:inline-block; width:440px; height:159px;\" width=\"440\" height=\"159\">\n\t\t\t</a>\n\t\t</td>\n\t</tr>\n\t<!-- BRANDBAR MOBILE // CLOSE // -->\n\t<!-- BRANDBAR DESKTOP DARK MODE // OPEN // -->\n\t<tr class=\"footerDarkDesktopShow footerDarkDesktopHide\" style=\"display:none;\">\n\t\t<td align=\"center\" style=\"padding-top:46px;padding-bottom:10px;\">\n\t\t\t<a href=\"https://www.marriottvacationclubs.com\" target=\"_blank\">\n\t\t\t\t<img src=\"https://s3.amazonaws.com/tmvc-email-static/email-footers/5_brandbar-desktop-dark.png\" alt=\"The Marriott Vacation Clubs: Marriott Vacation Club, Sheraton Vacation Club, Westin Vacation Club\" style=\"display:inline-block; width:638px; height:95px;\" width=\"638\" height=\"95\">\n\t\t\t</a>\n\t\t</td>\n\t</tr>\n\t<!-- BRANDBAR DESKTOP DARK MODE // CLOSE // -->\n\t<!-- BRANDBAR MOBILE DARK MODE // OPEN // -->\n\t<tr class=\"footerDarkMobileShow footerDarkMobileHide\" style=\"display:none;\">\n\t\t<td align=\"center\" style=\"padding-top:36px; padding-bottom:10px; text-align:center;\">\n\t\t\t<a href=\"https://www.marriottvacationclubs.com\" target=\"_blank\">\n\t\t\t\t<img class=\"footerWrapper footerAutoHeight\" src=\"https://s3.amazonaws.com/tmvc-email-static/email-footers/5_brandbar-mobile-dark.png\" alt=\"The Marriott Vacation Clubs: Marriott Vacation Club, Sheraton Vacation Club, Westin Vacation Club\" style=\"display:inline-block; width:440px; height:95px;\" width=\"440\" height=\"95\">\n\t\t\t</a>\n\t\t</td>\n\t</tr>\n\t<!-- BRANDBAR MOBILE DARK MODE // CLOSE // -->\n\t\n\t\n\t<!-- LEGAL // OPEN // -->\n\t<tr>\n\t\t<td class=\"footerAppleLinks footerDarkAppleLinks footerDarkColor footerPad2\" align=\"center\" style=\"padding-top:30px; padding-bottom:20px; padding-left:22px; padding-right:22px; color:#666666; font-size:12px; line-height:17px; font-family:Arial, sans-serif; text-align:center;\">\n\t\t\t\n\t\t\t&copy;<!-- # %%xtyear%% # -->2025 Marriott Vacation Club International. All Rights Reserved. Marriott Vacation Club International and the programs and products provided under the Marriott Vacation Club, Sheraton Vacation Club, and Westin Vacation Club brands are&nbsp;not owned, developed, or&nbsp;sold&nbsp;by Marriott International, Inc. Marriott Vacation Club International uses the Marriott&nbsp;marks under license from Marriott International,&nbsp;Inc. and&nbsp;its&nbsp;affiliates. \n\t\t\t<!-- SELLER OF TRAVEL FOR TNR OFFERS // OPEN --> \n\t\t\t<!--Marriott&nbsp;Resorts, Travel Company, Inc. and Westin Sheraton Vacation Services, Inc. are registered Florida Sellers of&nbsp;Travel, ST38869 and&nbsp;ST35697.--> \n\t\t\t<!-- SELLER OF TRAVEL FOR TNR OFFERS // CLOSE --> \n\t\t\tContact&nbsp;us&nbsp;at <a class=\"footerAppleLinks footerDarkAppleLinks nowrap\" href=\"#\" style=\"color:#666666; text-decoration:none; cursor:text;\">7812 Palm Parkway, Orlando,&nbsp;FL&nbsp;32836</a>.\n\t\t\t<!-- TIMESHARE DISCLOSURES FOR TR OFFERS // OPEN --> \n\t\t\t<br><br>\n\t\t\t<span style=\"font-size:14px;\">This advertising material is being used for&nbsp;the&nbsp;purpose of soliciting&nbsp;sales of&nbsp;timeshare&nbsp;interests.</span>\n\t\t\t<br><br>\n\t\t\t<strong>Any names and addresses acquired will be used for soliciting sales of timeshare interests. <br class=\"footerHide\">The&nbsp;complete offering terms are in an offering plan available&nbsp;from&nbsp;Sponsor.</strong>\n\t\t\t<!-- TIMESHARE DISCLOSURES FOR TR OFFERS // CLOSE --> \n\t\t</td>\n\t</tr>\n\t<!-- LEGAL // CLOSE // -->\n\t<!-- LINKS // OPEN // -->\n\t<tr>\n\t\t<td class=\"footerDarkColor\" align=\"center\" style=\"padding-top:8px; padding-bottom:4px; padding-left:2px; padding-right:2px; color:#666666; font-size:11px; line-height:18px; font-family:Arial, sans-serif; font-weight:bold; text-transform:uppercase; text-align:center;\">\n\t\t\t<a class=\"footerLinksNoUnderline footerDarkLinksNoUnderline\" href=\"https://www.marriottvacationclubs.com/s/privacy-policy\" style=\"color:#666666; text-decoration:none;\" target=\"_blank\">PRIVACY</a> &nbsp;•&nbsp; <a class=\"footerLinksNoUnderline footerDarkLinksNoUnderline\" href=\"https://www.marriottvacationclubs.com/s/terms-of-use\" style=\"color:#666666; text-decoration:none;\" target=\"_blank\">TERMS&nbsp;OF&nbsp;USE</a><br class=\"footerShow\" style=\"display:none;\"><span class=\"footerHide\"> &nbsp;•&nbsp; </span><a class=\"footerLinksNoUnderline footerDarkLinksNoUnderline\" href=\"https://www.marriottvacationclubs.com/s/state-and-legal-disclosures\" style=\"color:#666666; text-decoration:none;\" target=\"_blank\">LEGAL&nbsp;DISCLOSURES</a> &nbsp;•&nbsp; <a class=\"footerLinksNoUnderline footerDarkLinksNoUnderline\" href=\"%%view_email_url%%\" style=\"color:#666666; text-decoration:none;\" target=\"_blank\">WEB&nbsp;VIEW</a>\n\t\t</td>\n\t</tr>\n\t<!-- LINKS // CLOSE // -->\n\t<!-- EHO & PROJECT INFO // OPEN // -->\n\t<tr>\n\t\t<td class=\"footerAppleLinksNoUnderline footerDarkAppleLinksNoUnderline colorDarkGray\" align=\"center\" style=\"padding-top:20px; padding-bottom:40px; padding-left:2px; padding-right:2px; color:#666666; font-size:12px; line-height:20px; font-family:Arial, sans-serif; text-align:center;\">\n\t\t\t<img class=\"footerDarkEho\" border=\"0\" alt=\"Equal Housing Opportunity\" src=\"https://tmvc-email-static.s3.amazonaws.com/email-footers/eho.png\" style=\"display:inline; font-family:Arial, sans-serif; color:#666666; font-size:7px;\" width=\"17\" height=\"13\">&nbsp;&nbsp;Equal Housing Opportunity <span class=\"footerEhoShow\" style=\"display:none;\"><br><br></span><span class=\"footerHide\">&nbsp;|&nbsp; </span><span class=\"footerNoWrap\">MDC-25-000</span> &nbsp;|&nbsp; <span class=\"footerNoWrap\">25-1210-4123080</span>\n\t\t</td>\n\t</tr>\n\t<!-- EHO & PROJECT INFO // CLOSE // -->\n</table>\n<!-- FOOTER // CLOSE // -->\n</td></tr></table></div>\n<!-- BACKGROUND COLOR FIXES // CLOSE // -->\n<custom name=\"opencounter\" type=\"tracking\"/>\t\n</body>\n</html>\n",
      "deliveryMethod": "Email",
      "default": false
    },
    {
      "_links": {
        "template": {
          "href": "https://api.pingone.com/v1/environments/0ce2b42c-7022-46a8-923a-c04cf0d91a25/templates/strong_authentication"
        },
        "environment": {
          "href": "https://api.pingone.com/v1/environments/0ce2b42c-7022-46a8-923a-c04cf0d91a25"
        },
        "self": {
          "href": "https://api.pingone.com/v1/environments/0ce2b42c-7022-46a8-923a-c04cf0d91a25/templates/strong_authentication/contents/9a950568-09c9-4025-89d3-7a9a73ea1c75"
        }
      },
      "id": "9a950568-09c9-4025-89d3-7a9a73ea1c75",
      "environment": {
        "id": "0ce2b42c-7022-46a8-923a-c04cf0d91a25"
      },
      "createdAt": "2026-01-13T01:16:49.097Z",
      "updatedAt": "2026-01-13T01:16:49.097Z",
      "locale": "en",
      "template": {
        "id": "strong_authentication"
      },
      "content": "TMVC: Your secure sign-in verification code is ${otp}. Do not share this code. This code will expire in 10 minutes. If you did not request this, please ignore this message.",
      "deliveryMethod": "SMS",
      "default": false
    },
    {
      "_links": {
        "template": {
          "href": "https://api.pingone.com/v1/environments/0ce2b42c-7022-46a8-923a-c04cf0d91a25/templates/strong_authentication"
        },
        "environment": {
          "href": "https://api.pingone.com/v1/environments/0ce2b42c-7022-46a8-923a-c04cf0d91a25"
        },
        "self": {
          "href": "https://api.pingone.com/v1/environments/0ce2b42c-7022-46a8-923a-c04cf0d91a25/templates/strong_authentication/contents/7a354bd6-94b8-7e3b-0b4c-db15f4304d3b"
        }
      },
      "id": "7a354bd6-94b8-7e3b-0b4c-db15f4304d3b",
      "environment": {
        "id": "0ce2b42c-7022-46a8-923a-c04cf0d91a25"
      },
      "createdAt": "2021-09-26T08:34:36.000Z",
      "updatedAt": "2021-09-26T08:34:36.000Z",
      "locale": "ja",
      "template": {
        "id": "strong_authentication"
      },
      "content": "こんにちは <pause1sec>。あなたの認証コードは、 <sayCharValue>${OTP}</sayCharValue><pause1sec> です。繰り返します。あなたの認証コードは、 <sayCharValue>${OTP}</sayCharValue> です。",
      "deliveryMethod": "Voice",
      "default": true
    },
    {
      "_links": {
        "template": {
          "href": "https://api.pingone.com/v1/environments/0ce2b42c-7022-46a8-923a-c04cf0d91a25/templates/strong_authentication"
        },
        "environment": {
          "href": "https://api.pingone.com/v1/environments/0ce2b42c-7022-46a8-923a-c04cf0d91a25"
        },
        "self": {
          "href": "https://api.pingone.com/v1/environments/0ce2b42c-7022-46a8-923a-c04cf0d91a25/templates/strong_authentication/contents/790e70bb-a8ba-7fa2-2b48-a286a34765fb"
        }
      },
      "id": "790e70bb-a8ba-7fa2-2b48-a286a34765fb",
      "environment": {
        "id": "0ce2b42c-7022-46a8-923a-c04cf0d91a25"
      },
      "createdAt": "2021-09-26T08:34:36.000Z",
      "updatedAt": "2021-09-26T08:34:36.000Z",
      "locale": "fr",
      "template": {
        "id": "strong_authentication"
      },
      "content": "Votre code d'accès PingOne est : ${otp}",
      "deliveryMethod": "SMS",
      "default": true
    },
    {
      "_links": {
        "template": {
          "href": "https://api.pingone.com/v1/environments/0ce2b42c-7022-46a8-923a-c04cf0d91a25/templates/strong_authentication"
        },
        "environment": {
          "href": "https://api.pingone.com/v1/environments/0ce2b42c-7022-46a8-923a-c04cf0d91a25"
        },
        "self": {
          "href": "https://api.pingone.com/v1/environments/0ce2b42c-7022-46a8-923a-c04cf0d91a25/templates/strong_authentication/contents/776751bc-355f-75ce-06ee-72cabe86e72c"
        }
      },
      "id": "776751bc-355f-75ce-06ee-72cabe86e72c",
      "environment": {
        "id": "0ce2b42c-7022-46a8-923a-c04cf0d91a25"
      },
      "createdAt": "2021-09-26T08:34:36.000Z",
      "updatedAt": "2021-09-26T08:34:36.000Z",
      "locale": "nl",
      "template": {
        "id": "strong_authentication"
      },
      "content": "Uw PingOne-toeganscode is: ${otp}",
      "deliveryMethod": "SMS",
      "default": true
    },
    {
      "_links": {
        "template": {
          "href": "https://api.pingone.com/v1/environments/0ce2b42c-7022-46a8-923a-c04cf0d91a25/templates/strong_authentication"
        },
        "environment": {
          "href": "https://api.pingone.com/v1/environments/0ce2b42c-7022-46a8-923a-c04cf0d91a25"
        },
        "self": {
          "href": "https://api.pingone.com/v1/environments/0ce2b42c-7022-46a8-923a-c04cf0d91a25/templates/strong_authentication/contents/7338d4a4-58e3-702f-34e1-34c5e224ba2e"
        }
      },
      "id": "7338d4a4-58e3-702f-34e1-34c5e224ba2e",
      "environment": {
        "id": "0ce2b42c-7022-46a8-923a-c04cf0d91a25"
      },
      "createdAt": "2021-09-26T08:34:36.000Z",
      "updatedAt": "2021-09-26T08:34:36.000Z",
      "locale": "th",
      "template": {
        "id": "strong_authentication"
      },
      "title": "คำขอการยืนยันตัวตน PingOne",
      "body": "คุณมีคำขอการยืนยันตัวตนใหม่",
      "pushCategory": "BANNER_BUTTONS",
      "deliveryMethod": "Push",
      "default": true
    },
    {
      "_links": {
        "template": {
          "href": "https://api.pingone.com/v1/environments/0ce2b42c-7022-46a8-923a-c04cf0d91a25/templates/strong_authentication"
        },
        "environment": {
          "href": "https://api.pingone.com/v1/environments/0ce2b42c-7022-46a8-923a-c04cf0d91a25"
        },
        "self": {
          "href": "https://api.pingone.com/v1/environments/0ce2b42c-7022-46a8-923a-c04cf0d91a25/templates/strong_authentication/contents/71223e20-0aa7-7dfa-2c80-50924bf47cde"
        }
      },
      "id": "71223e20-0aa7-7dfa-2c80-50924bf47cde",
      "environment": {
        "id": "0ce2b42c-7022-46a8-923a-c04cf0d91a25"
      },
      "createdAt": "2021-09-26T08:34:36.000Z",
      "updatedAt": "2021-09-26T08:34:36.000Z",
      "locale": "nl",
      "template": {
        "id": "strong_authentication"
      },
      "title": "PingOne-authenticatieverzoek",
      "body": "U hebt een nieuw authenticatieverzoek.",
      "pushCategory": "BANNER_BUTTONS",
      "deliveryMethod": "Push",
      "default": true
    },
    {
      "_links": {
        "template": {
          "href": "https://api.pingone.com/v1/environments/0ce2b42c-7022-46a8-923a-c04cf0d91a25/templates/strong_authentication"
        },
        "environment": {
          "href": "https://api.pingone.com/v1/environments/0ce2b42c-7022-46a8-923a-c04cf0d91a25"
        },
        "self": {
          "href": "https://api.pingone.com/v1/environments/0ce2b42c-7022-46a8-923a-c04cf0d91a25/templates/strong_authentication/contents/6de6edbd-2325-7dd3-0d50-bf4448641051"
        }
      },
      "id": "6de6edbd-2325-7dd3-0d50-bf4448641051",
      "environment": {
        "id": "0ce2b42c-7022-46a8-923a-c04cf0d91a25"
      },
      "createdAt": "2021-09-26T08:34:36.000Z",
      "updatedAt": "2021-09-26T08:34:36.000Z",
      "locale": "zh",
      "template": {
        "id": "strong_authentication"
      },
      "content": "您好，<pause1sec>您的身份驗證代碼是 <sayCharValue>${OTP}</sayCharValue><pause1sec>。我重複，你的代碼是 <sayCharValue>${OTP}</sayCharValue>",
      "deliveryMethod": "Voice",
      "default": true
    },
    {
      "_links": {
        "template": {
          "href": "https://api.pingone.com/v1/environments/0ce2b42c-7022-46a8-923a-c04cf0d91a25/templates/strong_authentication"
        },
        "environment": {
          "href": "https://api.pingone.com/v1/environments/0ce2b42c-7022-46a8-923a-c04cf0d91a25"
        },
        "self": {
          "href": "https://api.pingone.com/v1/environments/0ce2b42c-7022-46a8-923a-c04cf0d91a25/templates/strong_authentication/contents/6d91c59c-6354-7852-2329-a7149c19f431"
        }
      },
      "id": "6d91c59c-6354-7852-2329-a7149c19f431",
      "environment": {
        "id": "0ce2b42c-7022-46a8-923a-c04cf0d91a25"
      },
      "createdAt": "2021-09-26T08:34:36.000Z",
      "updatedAt": "2021-09-26T08:34:36.000Z",
      "locale": "it",
      "template": {
        "id": "strong_authentication"
      },
      "title": "Richiesta di autenticazione PingOne",
      "body": "Hai una nuova richiesta di autenticazione.",
      "pushCategory": "BANNER_BUTTONS",
      "deliveryMethod": "Push",
      "default": true
    },
    {
      "_links": {
        "template": {
          "href": "https://api.pingone.com/v1/environments/0ce2b42c-7022-46a8-923a-c04cf0d91a25/templates/strong_authentication"
        },
        "environment": {
          "href": "https://api.pingone.com/v1/environments/0ce2b42c-7022-46a8-923a-c04cf0d91a25"
        },
        "self": {
          "href": "https://api.pingone.com/v1/environments/0ce2b42c-7022-46a8-923a-c04cf0d91a25/templates/strong_authentication/contents/6d603014-595e-7160-2ed1-f5be01eaaab2"
        }
      },
      "id": "6d603014-595e-7160-2ed1-f5be01eaaab2",
      "environment": {
        "id": "0ce2b42c-7022-46a8-923a-c04cf0d91a25"
      },
      "createdAt": "2021-09-26T08:34:36.000Z",
      "updatedAt": "2021-09-26T08:34:36.000Z",
      "locale": "es",
      "template": {
        "id": "strong_authentication"
      },
      "subject": "PingOne: Nueva solicitud de autenticación",
      "body": "Tu contraseña es: ${otp}",
      "deliveryMethod": "Email",
      "default": true
    },
    {
      "_links": {
        "template": {
          "href": "https://api.pingone.com/v1/environments/0ce2b42c-7022-46a8-923a-c04cf0d91a25/templates/strong_authentication"
        },
        "environment": {
          "href": "https://api.pingone.com/v1/environments/0ce2b42c-7022-46a8-923a-c04cf0d91a25"
        },
        "self": {
          "href": "https://api.pingone.com/v1/environments/0ce2b42c-7022-46a8-923a-c04cf0d91a25/templates/strong_authentication/contents/682a138d-74ca-71f9-2e2c-faae1333a25b"
        }
      },
      "id": "682a138d-74ca-71f9-2e2c-faae1333a25b",
      "environment": {
        "id": "0ce2b42c-7022-46a8-923a-c04cf0d91a25"
      },
      "createdAt": "2021-09-26T08:34:36.000Z",
      "updatedAt": "2021-09-26T08:34:36.000Z",
      "locale": "fr-CA",
      "template": {
        "id": "strong_authentication"
      },
      "content": "Votre code d'accès PingOne est: ${otp}",
      "deliveryMethod": "SMS",
      "default": true
    },
    {
      "_links": {
        "template": {
          "href": "https://api.pingone.com/v1/environments/0ce2b42c-7022-46a8-923a-c04cf0d91a25/templates/strong_authentication"
        },
        "environment": {
          "href": "https://api.pingone.com/v1/environments/0ce2b42c-7022-46a8-923a-c04cf0d91a25"
        },
        "self": {
          "href": "https://api.pingone.com/v1/environments/0ce2b42c-7022-46a8-923a-c04cf0d91a25/templates/strong_authentication/contents/67e97a30-3e01-7459-15c8-97b329a8bf40"
        }
      },
      "id": "67e97a30-3e01-7459-15c8-97b329a8bf40",
      "environment": {
        "id": "0ce2b42c-7022-46a8-923a-c04cf0d91a25"
      },
      "createdAt": "2021-09-26T08:34:36.000Z",
      "updatedAt": "2021-09-26T08:34:36.000Z",
      "locale": "th",
      "template": {
        "id": "strong_authentication"
      },
      "content": "รหัสผ่าน PingOne ของคุณคือ: ${otp}",
      "deliveryMethod": "SMS",
      "default": true
    },
    {
      "_links": {
        "template": {
          "href": "https://api.pingone.com/v1/environments/0ce2b42c-7022-46a8-923a-c04cf0d91a25/templates/strong_authentication"
        },
        "environment": {
          "href": "https://api.pingone.com/v1/environments/0ce2b42c-7022-46a8-923a-c04cf0d91a25"
        },
        "self": {
          "href": "https://api.pingone.com/v1/environments/0ce2b42c-7022-46a8-923a-c04cf0d91a25/templates/strong_authentication/contents/656ba4ac-13e0-7619-1849-8512cb75d69c"
        }
      },
      "id": "656ba4ac-13e0-7619-1849-8512cb75d69c",
      "environment": {
        "id": "0ce2b42c-7022-46a8-923a-c04cf0d91a25"
      },
      "createdAt": "2021-09-26T08:34:36.000Z",
      "updatedAt": "2021-09-26T08:34:36.000Z",
      "locale": "th",
      "template": {
        "id": "strong_authentication"
      },
      "subject": "PingOne: คำขอการยืนยันตัวตนใหม่",
      "body": "รหัสผ่านของคุณคือ: ${otp}",
      "deliveryMethod": "Email",
      "default": true
    },
    {
      "_links": {
        "template": {
          "href": "https://api.pingone.com/v1/environments/0ce2b42c-7022-46a8-923a-c04cf0d91a25/templates/strong_authentication"
        },
        "environment": {
          "href": "https://api.pingone.com/v1/environments/0ce2b42c-7022-46a8-923a-c04cf0d91a25"
        },
        "self": {
          "href": "https://api.pingone.com/v1/environments/0ce2b42c-7022-46a8-923a-c04cf0d91a25/templates/strong_authentication/contents/60285f69-18f8-7897-2ba1-4540fccba1d0"
        }
      },
      "id": "60285f69-18f8-7897-2ba1-4540fccba1d0",
      "environment": {
        "id": "0ce2b42c-7022-46a8-923a-c04cf0d91a25"
      },
      "createdAt": "2021-09-26T08:34:36.000Z",
      "updatedAt": "2021-09-26T08:34:36.000Z",
      "locale": "ru",
      "template": {
        "id": "strong_authentication"
      },
      "subject": "PingOne: Новый запрос на аутентификацию",
      "body": "Ваш секретный код: ${otp}",
      "deliveryMethod": "Email",
      "default": true
    },
    {
      "_links": {
        "template": {
          "href": "https://api.pingone.com/v1/environments/0ce2b42c-7022-46a8-923a-c04cf0d91a25/templates/strong_authentication"
        },
        "environment": {
          "href": "https://api.pingone.com/v1/environments/0ce2b42c-7022-46a8-923a-c04cf0d91a25"
        },
        "self": {
          "href": "https://api.pingone.com/v1/environments/0ce2b42c-7022-46a8-923a-c04cf0d91a25/templates/strong_authentication/contents/55acffce-072b-72e9-34da-72d7f336da97"
        }
      },
      "id": "55acffce-072b-72e9-34da-72d7f336da97",
      "environment": {
        "id": "0ce2b42c-7022-46a8-923a-c04cf0d91a25"
      },
      "createdAt": "2021-09-26T08:34:36.000Z",
      "updatedAt": "2021-09-26T08:34:36.000Z",
      "locale": "ru",
      "template": {
        "id": "strong_authentication"
      },
      "title": "Запрос аутентификации PingOne",
      "body": "У вас есть новый запрос на аутентификацию.",
      "pushCategory": "BANNER_BUTTONS",
      "deliveryMethod": "Push",
      "default": true
    },
    {
      "_links": {
        "template": {
          "href": "https://api.pingone.com/v1/environments/0ce2b42c-7022-46a8-923a-c04cf0d91a25/templates/strong_authentication"
        },
        "environment": {
          "href": "https://api.pingone.com/v1/environments/0ce2b42c-7022-46a8-923a-c04cf0d91a25"
        },
        "self": {
          "href": "https://api.pingone.com/v1/environments/0ce2b42c-7022-46a8-923a-c04cf0d91a25/templates/strong_authentication/contents/52eb1c56-edbb-7eea-1a50-f769e022a27a"
        }
      },
      "id": "52eb1c56-edbb-7eea-1a50-f769e022a27a",
      "environment": {
        "id": "0ce2b42c-7022-46a8-923a-c04cf0d91a25"
      },
      "createdAt": "2021-09-26T08:34:36.000Z",
      "updatedAt": "2021-09-26T08:34:36.000Z",
      "locale": "tr",
      "template": {
        "id": "strong_authentication"
      },
      "content": "PingOne şifreniz: ${otp}",
      "deliveryMethod": "SMS",
      "default": true
    },
    {
      "_links": {
        "template": {
          "href": "https://api.pingone.com/v1/environments/0ce2b42c-7022-46a8-923a-c04cf0d91a25/templates/strong_authentication"
        },
        "environment": {
          "href": "https://api.pingone.com/v1/environments/0ce2b42c-7022-46a8-923a-c04cf0d91a25"
        },
        "self": {
          "href": "https://api.pingone.com/v1/environments/0ce2b42c-7022-46a8-923a-c04cf0d91a25/templates/strong_authentication/contents/4c72fb14-ca78-7764-307e-c70bb1647633"
        }
      },
      "id": "4c72fb14-ca78-7764-307e-c70bb1647633",
      "environment": {
        "id": "0ce2b42c-7022-46a8-923a-c04cf0d91a25"
      },
      "createdAt": "2021-09-26T08:34:36.000Z",
      "updatedAt": "2021-09-26T08:34:36.000Z",
      "locale": "ja",
      "template": {
        "id": "strong_authentication"
      },
      "content": "あなたの PingOne パスコード： ${otp}",
      "deliveryMethod": "SMS",
      "default": true
    },
    {
      "_links": {
        "template": {
          "href": "https://api.pingone.com/v1/environments/0ce2b42c-7022-46a8-923a-c04cf0d91a25/templates/strong_authentication"
        },
        "environment": {
          "href": "https://api.pingone.com/v1/environments/0ce2b42c-7022-46a8-923a-c04cf0d91a25"
        },
        "self": {
          "href": "https://api.pingone.com/v1/environments/0ce2b42c-7022-46a8-923a-c04cf0d91a25/templates/strong_authentication/contents/410567d8-94e8-75c4-3943-ce527528a293"
        }
      },
      "id": "410567d8-94e8-75c4-3943-ce527528a293",
      "environment": {
        "id": "0ce2b42c-7022-46a8-923a-c04cf0d91a25"
      },
      "createdAt": "2021-09-26T08:34:36.000Z",
      "updatedAt": "2021-09-26T08:34:36.000Z",
      "locale": "nl",
      "template": {
        "id": "strong_authentication"
      },
      "content": "Hallo <pause1sec>, uw authenticatiecode is <sayCharValue>${OTP}</sayCharValue><pause1sec>Ik herhaal, uw code is <sayCharValue>${OTP}</sayCharValue>",
      "deliveryMethod": "Voice",
      "default": true
    },
    {
      "_links": {
        "template": {
          "href": "https://api.pingone.com/v1/environments/0ce2b42c-7022-46a8-923a-c04cf0d91a25/templates/strong_authentication"
        },
        "environment": {
          "href": "https://api.pingone.com/v1/environments/0ce2b42c-7022-46a8-923a-c04cf0d91a25"
        },
        "self": {
          "href": "https://api.pingone.com/v1/environments/0ce2b42c-7022-46a8-923a-c04cf0d91a25/templates/strong_authentication/contents/3fac9c4a-8c24-7ed1-1e72-4032ad2de1ce"
        }
      },
      "id": "3fac9c4a-8c24-7ed1-1e72-4032ad2de1ce",
      "environment": {
        "id": "0ce2b42c-7022-46a8-923a-c04cf0d91a25"
      },
      "createdAt": "2021-09-26T08:34:36.000Z",
      "updatedAt": "2021-09-26T08:34:36.000Z",
      "locale": "fr",
      "template": {
        "id": "strong_authentication"
      },
      "content": "Bonjour <pause1sec>, votre code d'authentification est <sayCharValue>${OTP}</sayCharValue><pause1sec>. Votre code est <sayCharValue>${OTP}</sayCharValue>",
      "deliveryMethod": "Voice",
      "default": true
    },
    {
      "_links": {
        "template": {
          "href": "https://api.pingone.com/v1/environments/0ce2b42c-7022-46a8-923a-c04cf0d91a25/templates/strong_authentication"
        },
        "environment": {
          "href": "https://api.pingone.com/v1/environments/0ce2b42c-7022-46a8-923a-c04cf0d91a25"
        },
        "self": {
          "href": "https://api.pingone.com/v1/environments/0ce2b42c-7022-46a8-923a-c04cf0d91a25/templates/strong_authentication/contents/3d5009b6-26e8-7bde-08ca-5dbfde1b471a"
        }
      },
      "id": "3d5009b6-26e8-7bde-08ca-5dbfde1b471a",
      "environment": {
        "id": "0ce2b42c-7022-46a8-923a-c04cf0d91a25"
      },
      "createdAt": "2021-09-26T08:34:36.000Z",
      "updatedAt": "2021-09-26T08:34:36.000Z",
      "locale": "de",
      "template": {
        "id": "strong_authentication"
      },
      "content": "Ihr PingOne Passcode lautet: ${otp}",
      "deliveryMethod": "SMS",
      "default": true
    },
    {
      "_links": {
        "template": {
          "href": "https://api.pingone.com/v1/environments/0ce2b42c-7022-46a8-923a-c04cf0d91a25/templates/strong_authentication"
        },
        "environment": {
          "href": "https://api.pingone.com/v1/environments/0ce2b42c-7022-46a8-923a-c04cf0d91a25"
        },
        "self": {
          "href": "https://api.pingone.com/v1/environments/0ce2b42c-7022-46a8-923a-c04cf0d91a25/templates/strong_authentication/contents/3acd647e-ec15-76e3-1eb1-0dbf9d86a83c"
        }
      },
      "id": "3acd647e-ec15-76e3-1eb1-0dbf9d86a83c",
      "environment": {
        "id": "0ce2b42c-7022-46a8-923a-c04cf0d91a25"
      },
      "createdAt": "2021-09-26T08:34:36.000Z",
      "updatedAt": "2021-09-26T08:34:36.000Z",
      "locale": "fr-CA",
      "template": {
        "id": "strong_authentication"
      },
      "subject": "PingOne Nouvelle demande d'authentification",
      "body": "Votre code d'accès est: ${otp}",
      "deliveryMethod": "Email",
      "default": true
    },
    {
      "_links": {
        "template": {
          "href": "https://api.pingone.com/v1/environments/0ce2b42c-7022-46a8-923a-c04cf0d91a25/templates/strong_authentication"
        },
        "environment": {
          "href": "https://api.pingone.com/v1/environments/0ce2b42c-7022-46a8-923a-c04cf0d91a25"
        },
        "self": {
          "href": "https://api.pingone.com/v1/environments/0ce2b42c-7022-46a8-923a-c04cf0d91a25/templates/strong_authentication/contents/3ab92bf0-4acd-77a7-0e27-8180e4a3c046"
        }
      },
      "id": "3ab92bf0-4acd-77a7-0e27-8180e4a3c046",
      "environment": {
        "id": "0ce2b42c-7022-46a8-923a-c04cf0d91a25"
      },
      "createdAt": "2021-09-26T08:34:36.000Z",
      "updatedAt": "2021-09-26T08:34:36.000Z",
      "locale": "de",
      "template": {
        "id": "strong_authentication"
      },
      "title": "PingOne Autorisierungsanfrage",
      "body": "Sie haben eine neue Autorisierungsanfrage.",
      "pushCategory": "BANNER_BUTTONS",
      "deliveryMethod": "Push",
      "default": true
    },
    {
      "_links": {
        "template": {
          "href": "https://api.pingone.com/v1/environments/0ce2b42c-7022-46a8-923a-c04cf0d91a25/templates/strong_authentication"
        },
        "environment": {
          "href": "https://api.pingone.com/v1/environments/0ce2b42c-7022-46a8-923a-c04cf0d91a25"
        },
        "self": {
          "href": "https://api.pingone.com/v1/environments/0ce2b42c-7022-46a8-923a-c04cf0d91a25/templates/strong_authentication/contents/2ba6f117-f4ce-75de-1f1d-50cf13ff54b5"
        }
      },
      "id": "2ba6f117-f4ce-75de-1f1d-50cf13ff54b5",
      "environment": {
        "id": "0ce2b42c-7022-46a8-923a-c04cf0d91a25"
      },
      "createdAt": "2021-09-26T08:34:36.000Z",
      "updatedAt": "2021-09-26T08:34:36.000Z",
      "locale": "es",
      "template": {
        "id": "strong_authentication"
      },
      "content": "Tu contraseña de PingOne es: ${otp}",
      "deliveryMethod": "SMS",
      "default": true
    },
    {
      "_links": {
        "template": {
          "href": "https://api.pingone.com/v1/environments/0ce2b42c-7022-46a8-923a-c04cf0d91a25/templates/strong_authentication"
        },
        "environment": {
          "href": "https://api.pingone.com/v1/environments/0ce2b42c-7022-46a8-923a-c04cf0d91a25"
        },
        "self": {
          "href": "https://api.pingone.com/v1/environments/0ce2b42c-7022-46a8-923a-c04cf0d91a25/templates/strong_authentication/contents/2aa4ce01-ec0a-711e-16f6-5cc0a5d6c43f"
        }
      },
      "id": "2aa4ce01-ec0a-711e-16f6-5cc0a5d6c43f",
      "environment": {
        "id": "0ce2b42c-7022-46a8-923a-c04cf0d91a25"
      },
      "createdAt": "2021-09-26T08:34:36.000Z",
      "updatedAt": "2021-09-26T08:34:36.000Z",
      "locale": "fr",
      "template": {
        "id": "strong_authentication"
      },
      "title": "Demande d'authentification PingOne",
      "body": "Vous avez une nouvelle demande d'authentification.",
      "pushCategory": "BANNER_BUTTONS",
      "deliveryMethod": "Push",
      "default": true
    },
    {
      "_links": {
        "template": {
          "href": "https://api.pingone.com/v1/environments/0ce2b42c-7022-46a8-923a-c04cf0d91a25/templates/strong_authentication"
        },
        "environment": {
          "href": "https://api.pingone.com/v1/environments/0ce2b42c-7022-46a8-923a-c04cf0d91a25"
        },
        "self": {
          "href": "https://api.pingone.com/v1/environments/0ce2b42c-7022-46a8-923a-c04cf0d91a25/templates/strong_authentication/contents/29033609-ebc7-7ded-018d-50a7d38ab00d"
        }
      },
      "id": "29033609-ebc7-7ded-018d-50a7d38ab00d",
      "environment": {
        "id": "0ce2b42c-7022-46a8-923a-c04cf0d91a25"
      },
      "createdAt": "2021-09-26T08:34:36.000Z",
      "updatedAt": "2021-09-26T08:34:36.000Z",
      "locale": "tr",
      "template": {
        "id": "strong_authentication"
      },
      "title": "PingOne Kimlik Doğrulama İsteği",
      "body": "Yeni bir kimlik doğrulama isteğiniz var.",
      "pushCategory": "BANNER_BUTTONS",
      "deliveryMethod": "Push",
      "default": true
    },
    {
      "_links": {
        "template": {
          "href": "https://api.pingone.com/v1/environments/0ce2b42c-7022-46a8-923a-c04cf0d91a25/templates/strong_authentication"
        },
        "environment": {
          "href": "https://api.pingone.com/v1/environments/0ce2b42c-7022-46a8-923a-c04cf0d91a25"
        },
        "self": {
          "href": "https://api.pingone.com/v1/environments/0ce2b42c-7022-46a8-923a-c04cf0d91a25/templates/strong_authentication/contents/28f8b484-785b-7170-324e-710cf39b96aa"
        }
      },
      "id": "28f8b484-785b-7170-324e-710cf39b96aa",
      "environment": {
        "id": "0ce2b42c-7022-46a8-923a-c04cf0d91a25"
      },
      "createdAt": "2021-09-26T08:34:36.000Z",
      "updatedAt": "2021-09-26T08:34:36.000Z",
      "locale": "zh",
      "template": {
        "id": "strong_authentication"
      },
      "title": "PingOne 身份驗證請求",
      "body": "您有一項新的身份驗證請求。",
      "pushCategory": "BANNER_BUTTONS",
      "deliveryMethod": "Push",
      "default": true
    },
    {
      "_links": {
        "template": {
          "href": "https://api.pingone.com/v1/environments/0ce2b42c-7022-46a8-923a-c04cf0d91a25/templates/strong_authentication"
        },
        "environment": {
          "href": "https://api.pingone.com/v1/environments/0ce2b42c-7022-46a8-923a-c04cf0d91a25"
        },
        "self": {
          "href": "https://api.pingone.com/v1/environments/0ce2b42c-7022-46a8-923a-c04cf0d91a25/templates/strong_authentication/contents/1ff000e3-3fed-77a5-02d4-f9d5d965d3ee"
        }
      },
      "id": "1ff000e3-3fed-77a5-02d4-f9d5d965d3ee",
      "environment": {
        "id": "0ce2b42c-7022-46a8-923a-c04cf0d91a25"
      },
      "createdAt": "2021-09-26T08:34:36.000Z",
      "updatedAt": "2021-09-26T08:34:36.000Z",
      "locale": "th",
      "template": {
        "id": "strong_authentication"
      },
      "content": "สวัสดี <pause1sec> รหัสยืนยันตัวตนของคุณคือ <sayCharValue>${OTP}</sayCharValue><pause1sec>ฉันขอย้ำ รหัสของคุณคือ <sayCharValue>${OTP}</sayCharValue>",
      "deliveryMethod": "Voice",
      "default": true
    },
    {
      "_links": {
        "template": {
          "href": "https://api.pingone.com/v1/environments/0ce2b42c-7022-46a8-923a-c04cf0d91a25/templates/strong_authentication"
        },
        "environment": {
          "href": "https://api.pingone.com/v1/environments/0ce2b42c-7022-46a8-923a-c04cf0d91a25"
        },
        "self": {
          "href": "https://api.pingone.com/v1/environments/0ce2b42c-7022-46a8-923a-c04cf0d91a25/templates/strong_authentication/contents/1bc0c90d-70e6-72b9-3981-43d34238987b"
        }
      },
      "id": "1bc0c90d-70e6-72b9-3981-43d34238987b",
      "environment": {
        "id": "0ce2b42c-7022-46a8-923a-c04cf0d91a25"
      },
      "createdAt": "2021-09-26T08:34:36.000Z",
      "updatedAt": "2021-09-26T08:34:36.000Z",
      "locale": "nl",
      "template": {
        "id": "strong_authentication"
      },
      "subject": "PingOne: Nieuw authenticatieverzoek",
      "body": "Uw toeganscode is: ${otp}",
      "deliveryMethod": "Email",
      "default": true
    },
    {
      "_links": {
        "template": {
          "href": "https://api.pingone.com/v1/environments/0ce2b42c-7022-46a8-923a-c04cf0d91a25/templates/strong_authentication"
        },
        "environment": {
          "href": "https://api.pingone.com/v1/environments/0ce2b42c-7022-46a8-923a-c04cf0d91a25"
        },
        "self": {
          "href": "https://api.pingone.com/v1/environments/0ce2b42c-7022-46a8-923a-c04cf0d91a25/templates/strong_authentication/contents/1acd20d1-5e55-7d8e-0491-0fae3234388b"
        }
      },
      "id": "1acd20d1-5e55-7d8e-0491-0fae3234388b",
      "environment": {
        "id": "0ce2b42c-7022-46a8-923a-c04cf0d91a25"
      },
      "createdAt": "2021-09-26T08:34:36.000Z",
      "updatedAt": "2021-09-26T08:34:36.000Z",
      "locale": "ja",
      "template": {
        "id": "strong_authentication"
      },
      "subject": "PingOne： 認証リクエスト",
      "body": "あなたのパスコード： ${otp`}",
      "deliveryMethod": "Email",
      "default": true
    },
    {
      "_links": {
        "template": {
          "href": "https://api.pingone.com/v1/environments/0ce2b42c-7022-46a8-923a-c04cf0d91a25/templates/strong_authentication"
        },
        "environment": {
          "href": "https://api.pingone.com/v1/environments/0ce2b42c-7022-46a8-923a-c04cf0d91a25"
        },
        "self": {
          "href": "https://api.pingone.com/v1/environments/0ce2b42c-7022-46a8-923a-c04cf0d91a25/templates/strong_authentication/contents/0efd5bd1-b51c-7966-0a88-fdb17a097bae"
        }
      },
      "id": "0efd5bd1-b51c-7966-0a88-fdb17a097bae",
      "environment": {
        "id": "0ce2b42c-7022-46a8-923a-c04cf0d91a25"
      },
      "createdAt": "2021-09-26T08:34:36.000Z",
      "updatedAt": "2021-09-26T08:34:36.000Z",
      "locale": "tr",
      "template": {
        "id": "strong_authentication"
      },
      "subject": "PingOne: Yeni kimlik doğrulama isteği",
      "body": "Şifreniz: ${otp}",
      "deliveryMethod": "Email",
      "default": true
    },
    {
      "_links": {
        "template": {
          "href": "https://api.pingone.com/v1/environments/0ce2b42c-7022-46a8-923a-c04cf0d91a25/templates/strong_authentication"
        },
        "environment": {
          "href": "https://api.pingone.com/v1/environments/0ce2b42c-7022-46a8-923a-c04cf0d91a25"
        },
        "self": {
          "href": "https://api.pingone.com/v1/environments/0ce2b42c-7022-46a8-923a-c04cf0d91a25/templates/strong_authentication/contents/05f46566-3f01-7cd7-2034-86d601c4ddb1"
        }
      },
      "id": "05f46566-3f01-7cd7-2034-86d601c4ddb1",
      "environment": {
        "id": "0ce2b42c-7022-46a8-923a-c04cf0d91a25"
      },
      "createdAt": "2021-09-26T08:34:36.000Z",
      "updatedAt": "2021-09-26T08:34:36.000Z",
      "locale": "de",
      "template": {
        "id": "strong_authentication"
      },
      "subject": "PingOne: Neue Autorisierungsanfrage",
      "body": "Ihr Passcode lautet: ${otp}",
      "deliveryMethod": "Email",
      "default": true
    },
    {
      "_links": {
        "template": {
          "href": "https://api.pingone.com/v1/environments/0ce2b42c-7022-46a8-923a-c04cf0d91a25/templates/strong_authentication"
        },
        "environment": {
          "href": "https://api.pingone.com/v1/environments/0ce2b42c-7022-46a8-923a-c04cf0d91a25"
        },
        "self": {
          "href": "https://api.pingone.com/v1/environments/0ce2b42c-7022-46a8-923a-c04cf0d91a25/templates/strong_authentication/contents/fb5ad701-6412-78ba-0567-5db7d8fa6446"
        }
      },
      "id": "fb5ad701-6412-78ba-0567-5db7d8fa6446",
      "environment": {
        "id": "0ce2b42c-7022-46a8-923a-c04cf0d91a25"
      },
      "createdAt": "2021-09-26T08:34:36.000Z",
      "updatedAt": "2021-09-26T08:34:36.000Z",
      "locale": "ko",
      "template": {
        "id": "strong_authentication"
      },
      "content": "안녕하세요 <pause1sec> 귀하의 인증 코드는 <sayCharValue>${OTP}</sayCharValue>입니다<pause1sec>다시 반복합니다. 귀하의 코드는 다음과 같습니다: <sayCharValue>${OTP}</sayCharValue>",
      "deliveryMethod": "Voice",
      "default": true
    },
    {
      "_links": {
        "template": {
          "href": "https://api.pingone.com/v1/environments/0ce2b42c-7022-46a8-923a-c04cf0d91a25/templates/strong_authentication"
        },
        "environment": {
          "href": "https://api.pingone.com/v1/environments/0ce2b42c-7022-46a8-923a-c04cf0d91a25"
        },
        "self": {
          "href": "https://api.pingone.com/v1/environments/0ce2b42c-7022-46a8-923a-c04cf0d91a25/templates/strong_authentication/contents/fa0d996e-a670-712b-1997-bc867e6a7c3d"
        }
      },
      "id": "fa0d996e-a670-712b-1997-bc867e6a7c3d",
      "environment": {
        "id": "0ce2b42c-7022-46a8-923a-c04cf0d91a25"
      },
      "createdAt": "2021-09-26T08:34:36.000Z",
      "updatedAt": "2021-09-26T08:34:36.000Z",
      "locale": "zh",
      "template": {
        "id": "strong_authentication"
      },
      "subject": "PingOne： 新的身份驗證請求",
      "body": "您的密碼是： ${otp}",
      "deliveryMethod": "Email",
      "default": true
    },
    {
      "_links": {
        "template": {
          "href": "https://api.pingone.com/v1/environments/0ce2b42c-7022-46a8-923a-c04cf0d91a25/templates/strong_authentication"
        },
        "environment": {
          "href": "https://api.pingone.com/v1/environments/0ce2b42c-7022-46a8-923a-c04cf0d91a25"
        },
        "self": {
          "href": "https://api.pingone.com/v1/environments/0ce2b42c-7022-46a8-923a-c04cf0d91a25/templates/strong_authentication/contents/f7937114-f496-7e81-21bb-b104ed2be03a"
        }
      },
      "id": "f7937114-f496-7e81-21bb-b104ed2be03a",
      "environment": {
        "id": "0ce2b42c-7022-46a8-923a-c04cf0d91a25"
      },
      "createdAt": "2021-09-26T08:34:36.000Z",
      "updatedAt": "2021-09-26T08:34:36.000Z",
      "locale": "de",
      "template": {
        "id": "strong_authentication"
      },
      "content": "Hallo <pause1sec>, Ihr Autorisierungscode lauetet <sayCharValue>${OTP}</sayCharValue><pause1sec>Ich wiederhole, Ihr Code lautet <sayCharValue>${OTP}</sayCharValue>",
      "deliveryMethod": "Voice",
      "default": true
    },
    {
      "_links": {
        "template": {
          "href": "https://api.pingone.com/v1/environments/0ce2b42c-7022-46a8-923a-c04cf0d91a25/templates/strong_authentication"
        },
        "environment": {
          "href": "https://api.pingone.com/v1/environments/0ce2b42c-7022-46a8-923a-c04cf0d91a25"
        },
        "self": {
          "href": "https://api.pingone.com/v1/environments/0ce2b42c-7022-46a8-923a-c04cf0d91a25/templates/strong_authentication/contents/e83c86df-e569-7459-0912-ad9ad2197fc2"
        }
      },
      "id": "e83c86df-e569-7459-0912-ad9ad2197fc2",
      "environment": {
        "id": "0ce2b42c-7022-46a8-923a-c04cf0d91a25"
      },
      "createdAt": "2021-09-26T08:34:36.000Z",
      "updatedAt": "2021-09-26T08:34:36.000Z",
      "locale": "ko",
      "template": {
        "id": "strong_authentication"
      },
      "content": "PingOne 비밀번호는 다음과 같습니다. ${otp}",
      "deliveryMethod": "SMS",
      "default": true
    },
    {
      "_links": {
        "template": {
          "href": "https://api.pingone.com/v1/environments/0ce2b42c-7022-46a8-923a-c04cf0d91a25/templates/strong_authentication"
        },
        "environment": {
          "href": "https://api.pingone.com/v1/environments/0ce2b42c-7022-46a8-923a-c04cf0d91a25"
        },
        "self": {
          "href": "https://api.pingone.com/v1/environments/0ce2b42c-7022-46a8-923a-c04cf0d91a25/templates/strong_authentication/contents/e23d04b3-d46b-756e-05dc-bd5f2f43129c"
        }
      },
      "id": "e23d04b3-d46b-756e-05dc-bd5f2f43129c",
      "environment": {
        "id": "0ce2b42c-7022-46a8-923a-c04cf0d91a25"
      },
      "createdAt": "2021-09-26T08:34:36.000Z",
      "updatedAt": "2021-09-26T08:34:36.000Z",
      "locale": "pt",
      "template": {
        "id": "strong_authentication"
      },
      "content": "O seu código de acesso do PingOne é: ${otp}",
      "deliveryMethod": "SMS",
      "default": true
    },
    {
      "_links": {
        "template": {
          "href": "https://api.pingone.com/v1/environments/0ce2b42c-7022-46a8-923a-c04cf0d91a25/templates/strong_authentication"
        },
        "environment": {
          "href": "https://api.pingone.com/v1/environments/0ce2b42c-7022-46a8-923a-c04cf0d91a25"
        },
        "self": {
          "href": "https://api.pingone.com/v1/environments/0ce2b42c-7022-46a8-923a-c04cf0d91a25/templates/strong_authentication/contents/e1fafbce-7c02-7b8a-0ad8-370743eb4e70"
        }
      },
      "id": "e1fafbce-7c02-7b8a-0ad8-370743eb4e70",
      "environment": {
        "id": "0ce2b42c-7022-46a8-923a-c04cf0d91a25"
      },
      "createdAt": "2021-09-26T08:34:36.000Z",
      "updatedAt": "2021-09-26T08:34:36.000Z",
      "locale": "ko",
      "template": {
        "id": "strong_authentication"
      },
      "title": "PingOne 인증 요청",
      "body": "새 인증 요청이 있습니다.",
      "pushCategory": "BANNER_BUTTONS",
      "deliveryMethod": "Push",
      "default": true
    },
    {
      "_links": {
        "template": {
          "href": "https://api.pingone.com/v1/environments/0ce2b42c-7022-46a8-923a-c04cf0d91a25/templates/strong_authentication"
        },
        "environment": {
          "href": "https://api.pingone.com/v1/environments/0ce2b42c-7022-46a8-923a-c04cf0d91a25"
        },
        "self": {
          "href": "https://api.pingone.com/v1/environments/0ce2b42c-7022-46a8-923a-c04cf0d91a25/templates/strong_authentication/contents/e0708f23-e1d1-7f2a-19ca-bf41828012dc"
        }
      },
      "id": "e0708f23-e1d1-7f2a-19ca-bf41828012dc",
      "environment": {
        "id": "0ce2b42c-7022-46a8-923a-c04cf0d91a25"
      },
      "createdAt": "2021-09-26T08:34:36.000Z",
      "updatedAt": "2021-09-26T08:34:36.000Z",
      "locale": "ko",
      "template": {
        "id": "strong_authentication"
      },
      "subject": "PingOne: 새 인증 요청",
      "body": "귀하의 비밀번호: ${otp}",
      "deliveryMethod": "Email",
      "default": true
    },
    {
      "_links": {
        "template": {
          "href": "https://api.pingone.com/v1/environments/0ce2b42c-7022-46a8-923a-c04cf0d91a25/templates/strong_authentication"
        },
        "environment": {
          "href": "https://api.pingone.com/v1/environments/0ce2b42c-7022-46a8-923a-c04cf0d91a25"
        },
        "self": {
          "href": "https://api.pingone.com/v1/environments/0ce2b42c-7022-46a8-923a-c04cf0d91a25/templates/strong_authentication/contents/da9996cd-327c-7d53-3fe4-7aea2c074c49"
        }
      },
      "id": "da9996cd-327c-7d53-3fe4-7aea2c074c49",
      "environment": {
        "id": "0ce2b42c-7022-46a8-923a-c04cf0d91a25"
      },
      "createdAt": "2021-09-26T08:34:36.000Z",
      "updatedAt": "2021-09-26T08:34:36.000Z",
      "locale": "pt",
      "template": {
        "id": "strong_authentication"
      },
      "title": "Pedido de autenticação do PingOne",
      "body": "Tem um novo pedido de autenticação.",
      "pushCategory": "BANNER_BUTTONS",
      "deliveryMethod": "Push",
      "default": true
    },
    {
      "_links": {
        "template": {
          "href": "https://api.pingone.com/v1/environments/0ce2b42c-7022-46a8-923a-c04cf0d91a25/templates/strong_authentication"
        },
        "environment": {
          "href": "https://api.pingone.com/v1/environments/0ce2b42c-7022-46a8-923a-c04cf0d91a25"
        },
        "self": {
          "href": "https://api.pingone.com/v1/environments/0ce2b42c-7022-46a8-923a-c04cf0d91a25/templates/strong_authentication/contents/d8939e2d-5cd5-731b-1928-dce33ed8ed16"
        }
      },
      "id": "d8939e2d-5cd5-731b-1928-dce33ed8ed16",
      "environment": {
        "id": "0ce2b42c-7022-46a8-923a-c04cf0d91a25"
      },
      "createdAt": "2021-09-26T08:34:36.000Z",
      "updatedAt": "2021-09-26T08:34:36.000Z",
      "locale": "tr",
      "template": {
        "id": "strong_authentication"
      },
      "content": "Merhaba <pause1sec> kimlik doğrulama kodunuz <sayCharValue>${OTP}</sayCharValue><pause1sec>Kodunuzu tekrarlıyorum <sayCharValue>${OTP}</sayCharValue>",
      "deliveryMethod": "Voice",
      "default": true
    },
    {
      "_links": {
        "template": {
          "href": "https://api.pingone.com/v1/environments/0ce2b42c-7022-46a8-923a-c04cf0d91a25/templates/strong_authentication"
        },
        "environment": {
          "href": "https://api.pingone.com/v1/environments/0ce2b42c-7022-46a8-923a-c04cf0d91a25"
        },
        "self": {
          "href": "https://api.pingone.com/v1/environments/0ce2b42c-7022-46a8-923a-c04cf0d91a25/templates/strong_authentication/contents/d7629c77-f4cc-7b18-1392-6c9844d4b6b5"
        }
      },
      "id": "d7629c77-f4cc-7b18-1392-6c9844d4b6b5",
      "environment": {
        "id": "0ce2b42c-7022-46a8-923a-c04cf0d91a25"
      },
      "createdAt": "2021-09-26T08:34:36.000Z",
      "updatedAt": "2021-09-26T08:34:36.000Z",
      "locale": "fr",
      "template": {
        "id": "strong_authentication"
      },
      "subject": "PingOne : Nouvelle demande d'authentification",
      "body": "Votre code d'accès est : ${otp}",
      "deliveryMethod": "Email",
      "default": true
    },
    {
      "_links": {
        "template": {
          "href": "https://api.pingone.com/v1/environments/0ce2b42c-7022-46a8-923a-c04cf0d91a25/templates/strong_authentication"
        },
        "environment": {
          "href": "https://api.pingone.com/v1/environments/0ce2b42c-7022-46a8-923a-c04cf0d91a25"
        },
        "self": {
          "href": "https://api.pingone.com/v1/environments/0ce2b42c-7022-46a8-923a-c04cf0d91a25/templates/strong_authentication/contents/cb5aefbe-0ceb-70a0-1255-4153cf1cafec"
        }
      },
      "id": "cb5aefbe-0ceb-70a0-1255-4153cf1cafec",
      "environment": {
        "id": "0ce2b42c-7022-46a8-923a-c04cf0d91a25"
      },
      "createdAt": "2021-09-26T08:34:36.000Z",
      "updatedAt": "2021-09-26T08:34:36.000Z",
      "locale": "fr-CA",
      "template": {
        "id": "strong_authentication"
      },
      "content": "Bonjour <pause1sec> votre code d'authentification est <sayCharValue>${OTP}</sayCharValue><pause1sec>Je répète, votre code est <sayCharValue>${OTP}</sayCharValue>",
      "deliveryMethod": "Voice",
      "default": true
    },
    {
      "_links": {
        "template": {
          "href": "https://api.pingone.com/v1/environments/0ce2b42c-7022-46a8-923a-c04cf0d91a25/templates/strong_authentication"
        },
        "environment": {
          "href": "https://api.pingone.com/v1/environments/0ce2b42c-7022-46a8-923a-c04cf0d91a25"
        },
        "self": {
          "href": "https://api.pingone.com/v1/environments/0ce2b42c-7022-46a8-923a-c04cf0d91a25/templates/strong_authentication/contents/c3e9524d-feb3-7df7-35f3-568042bb9bb7"
        }
      },
      "id": "c3e9524d-feb3-7df7-35f3-568042bb9bb7",
      "environment": {
        "id": "0ce2b42c-7022-46a8-923a-c04cf0d91a25"
      },
      "createdAt": "2021-09-26T08:34:36.000Z",
      "updatedAt": "2021-09-26T08:34:36.000Z",
      "locale": "ru",
      "template": {
        "id": "strong_authentication"
      },
      "content": "Ваш пароль PingOne: ${otp}",
      "deliveryMethod": "SMS",
      "default": true
    },
    {
      "_links": {
        "template": {
          "href": "https://api.pingone.com/v1/environments/0ce2b42c-7022-46a8-923a-c04cf0d91a25/templates/strong_authentication"
        },
        "environment": {
          "href": "https://api.pingone.com/v1/environments/0ce2b42c-7022-46a8-923a-c04cf0d91a25"
        },
        "self": {
          "href": "https://api.pingone.com/v1/environments/0ce2b42c-7022-46a8-923a-c04cf0d91a25/templates/strong_authentication/contents/aa97ec3e-5e45-762e-18a0-cf0ba515f8f7"
        }
      },
      "id": "aa97ec3e-5e45-762e-18a0-cf0ba515f8f7",
      "environment": {
        "id": "0ce2b42c-7022-46a8-923a-c04cf0d91a25"
      },
      "createdAt": "2021-09-26T08:34:36.000Z",
      "updatedAt": "2021-09-26T08:34:36.000Z",
      "locale": "pt",
      "template": {
        "id": "strong_authentication"
      },
      "content": "Olá <pause1sec> o seu código de autenticação é <sayCharValue>${OTP}</sayCharValue><pause1sec>Repito, o seu código é <sayCharValue>${OTP}</sayCharValue>",
      "deliveryMethod": "Voice",
      "default": true
    },
    {
      "_links": {
        "template": {
          "href": "https://api.pingone.com/v1/environments/0ce2b42c-7022-46a8-923a-c04cf0d91a25/templates/strong_authentication"
        },
        "environment": {
          "href": "https://api.pingone.com/v1/environments/0ce2b42c-7022-46a8-923a-c04cf0d91a25"
        },
        "self": {
          "href": "https://api.pingone.com/v1/environments/0ce2b42c-7022-46a8-923a-c04cf0d91a25/templates/strong_authentication/contents/a8d62f0c-ec79-709b-0e45-ea7e9ff67496"
        }
      },
      "id": "a8d62f0c-ec79-709b-0e45-ea7e9ff67496",
      "environment": {
        "id": "0ce2b42c-7022-46a8-923a-c04cf0d91a25"
      },
      "createdAt": "2021-09-26T08:34:36.000Z",
      "updatedAt": "2021-09-26T08:34:36.000Z",
      "locale": "it",
      "template": {
        "id": "strong_authentication"
      },
      "content": "Il tuo passcode PingOne è: ${otp}",
      "deliveryMethod": "SMS",
      "default": true
    },
    {
      "_links": {
        "template": {
          "href": "https://api.pingone.com/v1/environments/0ce2b42c-7022-46a8-923a-c04cf0d91a25/templates/strong_authentication"
        },
        "environment": {
          "href": "https://api.pingone.com/v1/environments/0ce2b42c-7022-46a8-923a-c04cf0d91a25"
        },
        "self": {
          "href": "https://api.pingone.com/v1/environments/0ce2b42c-7022-46a8-923a-c04cf0d91a25/templates/strong_authentication/contents/a7913d1b-2589-7a94-1604-23b6963cdddd"
        }
      },
      "id": "a7913d1b-2589-7a94-1604-23b6963cdddd",
      "environment": {
        "id": "0ce2b42c-7022-46a8-923a-c04cf0d91a25"
      },
      "createdAt": "2021-09-26T08:34:36.000Z",
      "updatedAt": "2021-09-26T08:34:36.000Z",
      "locale": "es",
      "template": {
        "id": "strong_authentication"
      },
      "content": "Hola, <pause1sec>, tu código de autenticación es <sayCharValue>${OTP}</sayCharValue><pause1sec>. Repito, tu código es <sayCharValue>${OTP}</sayCharValue>",
      "deliveryMethod": "Voice",
      "default": true
    },
    {
      "_links": {
        "template": {
          "href": "https://api.pingone.com/v1/environments/0ce2b42c-7022-46a8-923a-c04cf0d91a25/templates/strong_authentication"
        },
        "environment": {
          "href": "https://api.pingone.com/v1/environments/0ce2b42c-7022-46a8-923a-c04cf0d91a25"
        },
        "self": {
          "href": "https://api.pingone.com/v1/environments/0ce2b42c-7022-46a8-923a-c04cf0d91a25/templates/strong_authentication/contents/a4cc7e18-0ddd-7e65-0a09-1f1401f2dce8"
        }
      },
      "id": "a4cc7e18-0ddd-7e65-0a09-1f1401f2dce8",
      "environment": {
        "id": "0ce2b42c-7022-46a8-923a-c04cf0d91a25"
      },
      "createdAt": "2021-09-26T08:34:36.000Z",
      "updatedAt": "2021-09-26T08:34:36.000Z",
      "locale": "it",
      "template": {
        "id": "strong_authentication"
      },
      "content": "Ciao <pause1sec> il tuo codice di autenticazione è <sayCharValue>${OTP}</sayCharValue><pause1sec>Ripeto il tuo codice è <sayCharValue>${OTP}</sayCharValue>",
      "deliveryMethod": "Voice",
      "default": true
    },
    {
      "_links": {
        "template": {
          "href": "https://api.pingone.com/v1/environments/0ce2b42c-7022-46a8-923a-c04cf0d91a25/templates/strong_authentication"
        },
        "environment": {
          "href": "https://api.pingone.com/v1/environments/0ce2b42c-7022-46a8-923a-c04cf0d91a25"
        },
        "self": {
          "href": "https://api.pingone.com/v1/environments/0ce2b42c-7022-46a8-923a-c04cf0d91a25/templates/strong_authentication/contents/a3966891-fccb-786d-1cae-f753a625884f"
        }
      },
      "id": "a3966891-fccb-786d-1cae-f753a625884f",
      "environment": {
        "id": "0ce2b42c-7022-46a8-923a-c04cf0d91a25"
      },
      "createdAt": "2021-09-26T08:34:36.000Z",
      "updatedAt": "2021-09-26T08:34:36.000Z",
      "locale": "fr-CA",
      "template": {
        "id": "strong_authentication"
      },
      "title": "Demande d'authentification PingOne",
      "body": "Vous avez une nouvelle demande d'authentification.",
      "pushCategory": "BANNER_BUTTONS",
      "deliveryMethod": "Push",
      "default": true
    },
    {
      "_links": {
        "template": {
          "href": "https://api.pingone.com/v1/environments/0ce2b42c-7022-46a8-923a-c04cf0d91a25/templates/strong_authentication"
        },
        "environment": {
          "href": "https://api.pingone.com/v1/environments/0ce2b42c-7022-46a8-923a-c04cf0d91a25"
        },
        "self": {
          "href": "https://api.pingone.com/v1/environments/0ce2b42c-7022-46a8-923a-c04cf0d91a25/templates/strong_authentication/contents/9eb374c4-f413-74e5-06f7-9d0a5c6bb6e7"
        }
      },
      "id": "9eb374c4-f413-74e5-06f7-9d0a5c6bb6e7",
      "environment": {
        "id": "0ce2b42c-7022-46a8-923a-c04cf0d91a25"
      },
      "createdAt": "2021-09-26T08:34:36.000Z",
      "updatedAt": "2021-09-26T08:34:36.000Z",
      "locale": "pt",
      "template": {
        "id": "strong_authentication"
      },
      "subject": "PingOne: Novo pedido de autenticação",
      "body": "O seu código de acesso é: ${otp}",
      "deliveryMethod": "Email",
      "default": true
    },
    {
      "_links": {
        "template": {
          "href": "https://api.pingone.com/v1/environments/0ce2b42c-7022-46a8-923a-c04cf0d91a25/templates/strong_authentication"
        },
        "environment": {
          "href": "https://api.pingone.com/v1/environments/0ce2b42c-7022-46a8-923a-c04cf0d91a25"
        },
        "self": {
          "href": "https://api.pingone.com/v1/environments/0ce2b42c-7022-46a8-923a-c04cf0d91a25/templates/strong_authentication/contents/9ac748c7-8363-7919-3cb9-28fafc688cc4"
        }
      },
      "id": "9ac748c7-8363-7919-3cb9-28fafc688cc4",
      "environment": {
        "id": "0ce2b42c-7022-46a8-923a-c04cf0d91a25"
      },
      "createdAt": "2021-09-26T08:34:36.000Z",
      "updatedAt": "2021-09-26T08:34:36.000Z",
      "locale": "ru",
      "template": {
        "id": "strong_authentication"
      },
      "content": "Здравствуйте, <pause1sec>! Ваш код аутентификации <sayCharValue>${OTP}</sayCharValue><pause1sec>. Повторяю, Ваш код: <sayCharValue>${OTP}</sayCharValue>",
      "deliveryMethod": "Voice",
      "default": true
    },
    {
      "_links": {
        "template": {
          "href": "https://api.pingone.com/v1/environments/0ce2b42c-7022-46a8-923a-c04cf0d91a25/templates/strong_authentication"
        },
        "environment": {
          "href": "https://api.pingone.com/v1/environments/0ce2b42c-7022-46a8-923a-c04cf0d91a25"
        },
        "self": {
          "href": "https://api.pingone.com/v1/environments/0ce2b42c-7022-46a8-923a-c04cf0d91a25/templates/strong_authentication/contents/961650d7-5af7-724b-2f07-83d1aa296c32"
        }
      },
      "id": "961650d7-5af7-724b-2f07-83d1aa296c32",
      "environment": {
        "id": "0ce2b42c-7022-46a8-923a-c04cf0d91a25"
      },
      "createdAt": "2021-09-26T08:34:36.000Z",
      "updatedAt": "2021-09-26T08:34:36.000Z",
      "locale": "zh",
      "template": {
        "id": "strong_authentication"
      },
      "content": "您的 PingOne 密碼是： ${otp}",
      "deliveryMethod": "SMS",
      "default": true
    },
    {
      "_links": {
        "template": {
          "href": "https://api.pingone.com/v1/environments/0ce2b42c-7022-46a8-923a-c04cf0d91a25/templates/strong_authentication"
        },
        "environment": {
          "href": "https://api.pingone.com/v1/environments/0ce2b42c-7022-46a8-923a-c04cf0d91a25"
        },
        "self": {
          "href": "https://api.pingone.com/v1/environments/0ce2b42c-7022-46a8-923a-c04cf0d91a25/templates/strong_authentication/contents/92934ada-7e3b-788e-3c8a-72fb14497122"
        }
      },
      "id": "92934ada-7e3b-788e-3c8a-72fb14497122",
      "environment": {
        "id": "0ce2b42c-7022-46a8-923a-c04cf0d91a25"
      },
      "createdAt": "2021-09-26T08:34:36.000Z",
      "updatedAt": "2021-09-26T08:34:36.000Z",
      "locale": "it",
      "template": {
        "id": "strong_authentication"
      },
      "subject": "PingOne: Nuova richiesta di autenticazione",
      "body": "Il tuo passcode è: ${otp}",
      "deliveryMethod": "Email",
      "default": true
    },
    {
      "_links": {
        "template": {
          "href": "https://api.pingone.com/v1/environments/0ce2b42c-7022-46a8-923a-c04cf0d91a25/templates/strong_authentication"
        },
        "environment": {
          "href": "https://api.pingone.com/v1/environments/0ce2b42c-7022-46a8-923a-c04cf0d91a25"
        },
        "self": {
          "href": "https://api.pingone.com/v1/environments/0ce2b42c-7022-46a8-923a-c04cf0d91a25/templates/strong_authentication/contents/919e549d-9759-789f-38e6-fda63e706519"
        }
      },
      "id": "919e549d-9759-789f-38e6-fda63e706519",
      "environment": {
        "id": "0ce2b42c-7022-46a8-923a-c04cf0d91a25"
      },
      "createdAt": "2021-09-26T08:34:36.000Z",
      "updatedAt": "2021-09-26T08:34:36.000Z",
      "locale": "es",
      "template": {
        "id": "strong_authentication"
      },
      "title": "Solicitud de autenticación de PingOne",
      "body": "TIenes una nueva solicitud de autenticación.",
      "pushCategory": "BANNER_BUTTONS",
      "deliveryMethod": "Push",
      "default": true
    },
    {
      "_links": {
        "template": {
          "href": "https://api.pingone.com/v1/environments/0ce2b42c-7022-46a8-923a-c04cf0d91a25/templates/strong_authentication"
        },
        "environment": {
          "href": "https://api.pingone.com/v1/environments/0ce2b42c-7022-46a8-923a-c04cf0d91a25"
        },
        "self": {
          "href": "https://api.pingone.com/v1/environments/0ce2b42c-7022-46a8-923a-c04cf0d91a25/templates/strong_authentication/contents/811e2563-31f9-7679-2511-04f5da76e9e7"
        }
      },
      "id": "811e2563-31f9-7679-2511-04f5da76e9e7",
      "environment": {
        "id": "0ce2b42c-7022-46a8-923a-c04cf0d91a25"
      },
      "createdAt": "2021-09-26T08:34:36.000Z",
      "updatedAt": "2021-09-26T08:34:36.000Z",
      "locale": "ja",
      "template": {
        "id": "strong_authentication"
      },
      "title": "PingOne 認証リクエスト",
      "body": "認証リクエストが届いています",
      "pushCategory": "BANNER_BUTTONS",
      "deliveryMethod": "Push",
      "default": true
    },
    {
      "_links": {
        "template": {
          "href": "https://api.pingone.com/v1/environments/0ce2b42c-7022-46a8-923a-c04cf0d91a25/templates/strong_authentication"
        },
        "environment": {
          "href": "https://api.pingone.com/v1/environments/0ce2b42c-7022-46a8-923a-c04cf0d91a25"
        },
        "self": {
          "href": "https://api.pingone.com/v1/environments/0ce2b42c-7022-46a8-923a-c04cf0d91a25/templates/strong_authentication/contents/73fa2d8c-17fb-72a3-37ba-f754c3a6844c"
        }
      },
      "id": "73fa2d8c-17fb-72a3-37ba-f754c3a6844c",
      "environment": {
        "id": "0ce2b42c-7022-46a8-923a-c04cf0d91a25"
      },
      "createdAt": "2021-02-18T07:04:18.000Z",
      "updatedAt": "2021-02-18T07:04:18.000Z",
      "locale": "en",
      "template": {
        "id": "strong_authentication"
      },
      "content": "Hello <pause1sec> your authentication code is <sayCharValue>${otp}</sayCharValue><pause1sec><pause1sec><repeatMessage val=2>I repeat <pause1sec>your code is <sayCharValue>${otp}</sayCharValue></repeatMessage>",
      "deliveryMethod": "Voice",
      "default": true
    },
    {
      "_links": {
        "template": {
          "href": "https://api.pingone.com/v1/environments/0ce2b42c-7022-46a8-923a-c04cf0d91a25/templates/strong_authentication"
        },
        "environment": {
          "href": "https://api.pingone.com/v1/environments/0ce2b42c-7022-46a8-923a-c04cf0d91a25"
        },
        "self": {
          "href": "https://api.pingone.com/v1/environments/0ce2b42c-7022-46a8-923a-c04cf0d91a25/templates/strong_authentication/contents/4a1a1d44-5357-76f4-2c31-db2bfc232e44"
        }
      },
      "id": "4a1a1d44-5357-76f4-2c31-db2bfc232e44",
      "environment": {
        "id": "0ce2b42c-7022-46a8-923a-c04cf0d91a25"
      },
      "createdAt": "2018-12-17T13:34:36.000Z",
      "updatedAt": "2018-12-17T13:34:36.000Z",
      "locale": "en",
      "template": {
        "id": "strong_authentication"
      },
      "title": "PingOne Authentication Request",
      "body": "You have a new authentication request.",
      "pushCategory": "BANNER_BUTTONS",
      "deliveryMethod": "Push",
      "default": true
    },
    {
      "_links": {
        "template": {
          "href": "https://api.pingone.com/v1/environments/0ce2b42c-7022-46a8-923a-c04cf0d91a25/templates/strong_authentication"
        },
        "environment": {
          "href": "https://api.pingone.com/v1/environments/0ce2b42c-7022-46a8-923a-c04cf0d91a25"
        },
        "self": {
          "href": "https://api.pingone.com/v1/environments/0ce2b42c-7022-46a8-923a-c04cf0d91a25/templates/strong_authentication/contents/11213028-1384-7b83-28b4-0e24c35a5476"
        }
      },
      "id": "11213028-1384-7b83-28b4-0e24c35a5476",
      "environment": {
        "id": "0ce2b42c-7022-46a8-923a-c04cf0d91a25"
      },
      "createdAt": "2018-08-27T05:34:51.000Z",
      "updatedAt": "2018-12-17T13:34:36.000Z",
      "locale": "en",
      "template": {
        "id": "strong_authentication"
      },
      "subject": "PingOne: New authentication request",
      "body": "Your passcode is: ${otp}",
      "deliveryMethod": "Email",
      "default": true
    },
    {
      "_links": {
        "template": {
          "href": "https://api.pingone.com/v1/environments/0ce2b42c-7022-46a8-923a-c04cf0d91a25/templates/strong_authentication"
        },
        "environment": {
          "href": "https://api.pingone.com/v1/environments/0ce2b42c-7022-46a8-923a-c04cf0d91a25"
        },
        "self": {
          "href": "https://api.pingone.com/v1/environments/0ce2b42c-7022-46a8-923a-c04cf0d91a25/templates/strong_authentication/contents/a45935a6-8926-749b-3f32-5dea38f5a3d0"
        }
      },
      "id": "a45935a6-8926-749b-3f32-5dea38f5a3d0",
      "environment": {
        "id": "0ce2b42c-7022-46a8-923a-c04cf0d91a25"
      },
      "createdAt": "2018-08-27T05:34:51.000Z",
      "updatedAt": "2018-12-17T13:34:36.000Z",
      "locale": "en",
      "template": {
        "id": "strong_authentication"
      },
      "content": "Your PingOne passcode is: ${otp}",
      "deliveryMethod": "SMS",
      "default": true
    }
  ]
}